purplship/mappers/fedex_express/__init__.py
purplship/mappers/fedex_express/mapper.py
purplship/mappers/fedex_express/proxy.py
purplship/mappers/fedex_express/settings.py
purplship.fedex_express-2021.2.dist-info/WHEEL
purplship.fedex_express-2021.2.dist-info/METADATA
purplship.fedex_express-2021.2.dist-info/RECORD
