Metadata-Version: 2.1
Name: purplship.fedex-express
Version: 2021.2
Summary: Purplship - FedEx Express Shipping Extension
Home-page: https://sdk.purplship.com
License: LGPLv3
Author: Dan Kobina
Author-email: danielkobina@gmail.com
Requires-Python: >=3.7,<4.0
Classifier: Intended Audience :: Developers
Classifier: License :: OSI Approved :: GNU Lesser General Public License v3 (LGPLv3)
Classifier: License :: Other/Proprietary License
Classifier: Operating System :: OS Independent
Classifier: Programming Language :: Python :: 3
Classifier: Programming Language :: Python :: 3.7
Classifier: Programming Language :: Python :: 3.8
Classifier: Programming Language :: Python :: 3.9
Requires-Dist: purplship.fedex (>=2021.2,<2022.0)
Project-URL: Repository, https://github.com/PurplShip/purplship
